dkist_sphinx_theme/__init__.py
dkist_sphinx_theme/create_intersphinx_mapping.py
dkist_sphinx_theme/create_requirements_table.py
dkist_sphinx_theme/create_workflow_diagram.py
dkist_sphinx_theme/autoapi_templates/python/module.rst
dkist_sphinx_theme/conf/__init__.py
dkist_sphinx_theme/conf/autoapi.py
dkist_sphinx_theme/conf/core.py
dkist_sphinx_theme/conf/theme.py
dkist_sphinx_theme/conf/verify_requirements.py
dkist_sphinx_theme/tests/__init__.py
dkist_sphinx_theme/tests/test_defined_mappings.py
dkist_sphinx_theme/tests/test_import.py
dkist_sphinx_theme/theme/dkist/theme.conf
dkist_sphinx_theme/theme/dkist/static/css/dkist.css
dkist_sphinx_theme/theme/dkist/static/img/dkist-logo-v5-blue-text.png
dkist_sphinx_theme/theme/dkist/static/img/dkist-logo-v5-white-text.png
dkist_sphinx_theme/theme/dkist/static/img/favico.ico
dkist_sphinx_theme/theme/dkist/static/img/nso_logo.png
dkist_sphinx_theme-2.0.4.dist-info/licenses/LICENSE.rst
dkist_sphinx_theme-2.0.4.dist-info/METADATA
dkist_sphinx_theme-2.0.4.dist-info/WHEEL
dkist_sphinx_theme-2.0.4.dist-info/entry_points.txt
dkist_sphinx_theme-2.0.4.dist-info/top_level.txt
dkist_sphinx_theme-2.0.4.dist-info/RECORD
